naowidgets.py
naowidgets-0.1.1.dist-info/LICENSE
naowidgets-0.1.1.dist-info/METADATA
naowidgets-0.1.1.dist-info/WHEEL
naowidgets-0.1.1.dist-info/top_level.txt
naowidgets-0.1.1.dist-info/RECORD
