Metadata-Version: 2.1
Name: naowidgets
Version: 0.1.1
Summary: A small library with useful widgets for NAO in Jupyter.
Home-page: https://github.com/NaosClassroom/naowidgets
Author: Emile Kroeger
Author-email: e.kroeger@unitedrobotics.group
Platform: any
Classifier: Programming Language :: Python :: 3
Classifier: License :: OSI Approved :: BSD License
Classifier: Operating System :: OS Independent
Requires-Python: >=3.6
License-File: LICENSE
Requires-Dist: ipywidgets
Requires-Dist: IPython
